__init__.py
config.py
main.py
se_config.py
silent_engine.py
silent/__init__.py
silent/se_config.py
silent/Class/Property.py
silent/Class/__init__.py
silent/Decorator/Decorator.py
silent/Decorator/DecoratorArgument.py
silent/Decorator/__init__.py
silent/DocBlock/ClassMethodDocBlock.py
silent/DocBlock/ModuleDocBlock.py
silent/DocBlock/PackageDocBlock.py
silent/DocBlock/__init__.py
silent/DocBlock/_templates/docblock_template.py
silent/EntityBase/__init__.py
silent/Import/ImportStatement.py
silent/Import/__init__.py
silent/Method/Method.py
silent/Method/MethodArgument.py
silent/Method/__init__.py
silent/Module/__init__.py
silent/Package/__init__.py
silent/settings/__init__.py
silent/settings/types.py
colemen_silent_engine-0.1.13.dist-info/METADATA
colemen_silent_engine-0.1.13.dist-info/WHEEL
colemen_silent_engine-0.1.13.dist-info/top_level.txt
colemen_silent_engine-0.1.13.dist-info/RECORD
